CHANGELOG.txt
LICENSE.txt
MANIFEST.in
README.txt
setup.py
hbasicpump/__init__.py
hbasicpump.egg-info/PKG-INFO
hbasicpump.egg-info/SOURCES.txt
hbasicpump.egg-info/dependency_links.txt
hbasicpump.egg-info/top_level.txt
methods/functions.py
methods/greet.py