Metadata-Version: 1.1
Name: hbasicpump
Version: 0.0.4
Summary: A very basic application
Home-page: UNKNOWN
Author: Camil Milos
Author-email: mcamil16@yahoo.com
License: MIT
Keywords: calculator
Platform: UNKNOWN
Classifier: Development Status :: 5 - Production/Stable
Classifier: Intended Audience :: Education
Classifier: Operating System :: Microsoft :: Windows :: Windows 10
Classifier: License :: OSI Approved :: MIT License
Classifier: Programming Language :: Python :: 3
